{"id": "niclassify.gui", "path": "c:\\Users\\J C\\Documents\\GitHub\\niclassify\\niclassify\\gui.py", "mtime": 1591640117, "size": 8173, "hash": "e3a06e992e0318bce7928436a55fd014", "data_mtime": 1591640087, "dependencies": ["logging", "os", "shutil", "subprocess", "sys", "threading", "tkinter", "tkinter.filedialog", "tkinter.ttk", "builtins", "_importlib_modulespec", "abc", "typing"], "suppressed": ["matplotlib.pyplot", "matplotlib", "numpy", "pandas", "seaborn", "joblib", "xlrd", "core", "core.StandardProgram", "core.classifiers", "tkui.elements", "tkui.utilities"], "child_modules": [], "options": {"disallow_any_generics": false, "disallow_any_decorated": false, "disallow_untyped_decorators": false, "disallow_any_unimported": false, "local_partial_types": false, "disallow_any_explicit": false, "strict_optional": true, "disallow_incomplete_defs": false, "strict_optional_whitelist": null, "allow_untyped_globals": false, "strict_equality": false, "warn_return_any": false, "always_false": [], "plugins": [], "warn_no_return": true, "mypyc": false, "disallow_untyped_calls": false, "new_semantic_analyzer": false, "warn_unused_ignores": false, "disallow_any_expr": false, "ignore_missing_imports": true, "platform": "win32", "disallow_untyped_defs": false, "follow_imports": "silent", "no_implicit_optional": false, "check_untyped_defs": false, "always_true": [], "allow_redefinition": false, "follow_imports_for_stubs": false, "bazel": false, "ignore_errors": false, "disallow_subclassing_any": false, "show_none_errors": true}, "dep_prios": [10, 10, 10, 10, 10, 10, 10, 10, 10, 5, 30, 30, 30, 10, 20, 10, 10, 10, 5, 5, 5, 5, 5, 5, 5], "dep_lines": [1, 2, 3, 4, 5, 6, 12, 16, 17, 1, 1, 1, 1, 8, 8, 9, 10, 11, 15, 18, 21, 22, 23, 24, 25], "interface_hash": "91e4d0c309fd91706327387e96ee22e1", "version_id": "0.701", "ignore_all": false}